zhu/__init__.py
zhu/_main.py
scancopy-1.1.5.dist-info/METADATA
scancopy-1.1.5.dist-info/WHEEL
scancopy-1.1.5.dist-info/top_level.txt
scancopy-1.1.5.dist-info/RECORD
