Metadata-Version: 2.1
Name: scancopy
Version: 1.1.5
Summary: scancopy
Home-page: UNKNOWN
Author: jiaobenxiaozi
Author-email: 183732521@qq.com
License: UNKNOWN
Platform: UNKNOWN
Requires-Python: >=3.6
Requires-Dist: tk
